chombopy/__init__.py
chombopy/chombopy.py
chombopy/inputs.py
chombopy/plotting.py
chombopy/time_table.py
chombopy/xarray.py
chombopy-1.0.1.dist-info/LICENSE
chombopy-1.0.1.dist-info/METADATA
chombopy-1.0.1.dist-info/WHEEL
chombopy-1.0.1.dist-info/top_level.txt
chombopy-1.0.1.dist-info/RECORD
