Metadata-Version: 2.1
Name: chombopy
Version: 1.0.1
Summary: Running, analysing and plotting Chombo simulations
Home-page: https://github.com/jrgparkinson/chombopy
Author: Jamie Parkinson
Author-email: jamie.parkinson@gmail.com
License: MIT
Classifier: Programming Language :: Python :: 3
Classifier: License :: OSI Approved :: MIT License
Classifier: Operating System :: OS Independent
Requires-Python: >=3.10
License-File: LICENSE
Requires-Dist: numpy ==1.22.1
Requires-Dist: matplotlib
Requires-Dist: Shapely
Requires-Dist: h5py
Requires-Dist: pandas
Requires-Dist: geopandas
Requires-Dist: xarray
Requires-Dist: pytest-cov
Requires-Dist: coverage
Requires-Dist: pytest-html
Requires-Dist: wheel
Requires-Dist: sphinx
